[{"name":"sym.boost::serialization::no_rtti_system::extended_type_info_no_rtti_0::extended_type_info_no_rtti_0__","offset":134218016,"ninstr":0,"nargs":1,"nlocals":0,"size":33,"stack":0,"type":"sym","blocks":[{"offset":134218016,"size":33,"ops":[{"offset":134218016,"ptr":134218023,"esil":"rip,rax,=","refptr":true,"fcn_addr":134218016,"fcn_last":134218042,"size":7,"opcode":"lea rax, [rip]","disasm":"lea rax, [0x08000127]","bytes":"488d0500000000","family":"cpu","type":"lea","reloc":true,"type_num":33,"type2_num":0,"flags":["sym.boost::serialization::no_rtti_system::extended_type_info_no_rtti_0::extended_type_info_no_rtti_0__"],"comment":"Ym9vc3Q6OnNlcmlhbGl6YXRpb246Om5vX3J0dGlfc3lzdGVtOjpleHRlbmRlZF90eXBlX2luZm9fbm9fcnR0aV8wOjp+ZXh0ZW5kZWRfdHlwZV9pbmZvX25vX3J0dGlfMCgp","refs":[{"addr":134218023,"type":"DATA","perm":"r--"}]},{"offset":134218023,"esil":"rbp,8,rsp,-,=[8],8,rsp,-=","refptr":false,"fcn_addr":134218016,"fcn_last":134218048,"size":1,"opcode":"push rbp","disasm":"push rbp","bytes":"55","family":"cpu","type":"rpush","reloc":false,"type_num":268435468,"type2_num":0,"xrefs":[{"addr":134218016,"type":"DATA","perm":"r--"}]},{"offset":134218024,"esil":"rdi,rbp,=","refptr":false,"fcn_addr":134218016,"fcn_last":134218046,"size":3,"opcode":"mov rbp, rdi","disasm":"mov rbp, rdi","bytes":"4889fd","family":"cpu","type":"mov","reloc":false,"type_num":9,"type2_num":0},{"offset":134218027,"esil":"rax,rdi,=[8]","refptr":true,"fcn_addr":134218016,"fcn_last":134218046,"size":3,"opcode":"mov qword [rdi], rax","disasm":"mov qword [rdi], rax","bytes":"488907","family":"cpu","type":"mov","reloc":false,"type_num":9,"type2_num":0},{"offset":134218030,"esil":"134218035,rip,8,rsp,-=,rsp,=[8],rip,=","refptr":false,"fcn_addr":134218016,"fcn_last":134218044,"size":5,"opcode":"call 0x8000133","disasm":"call _ZN5boost13serialization18extended_type_infoD2Ev","bytes":"e800000000","family":"cpu","type":"call","reloc":true,"type_num":3,"type2_num":0,"jump":134218035,"fail":134218035,"refs":[{"addr":134218035,"type":"CALL","perm":"--x"}]},{"offset":134218035,"esil":"rbp,rdi,=","refptr":false,"fcn_addr":134218016,"fcn_last":134218046,"size":3,"opcode":"mov rdi, rbp","disasm":"mov rdi, rbp","bytes":"4889ef","family":"cpu","type":"mov","reloc":false,"type_num":9,"type2_num":0,"xrefs":[{"addr":134218030,"type":"CALL","perm":"--x"}]},{"offset":134218038,"ptr":24,"val":24,"esil":"24,rsi,=","refptr":false,"fcn_addr":134218016,"fcn_last":134218044,"size":5,"opcode":"mov esi, 0x18","disasm":"mov esi, 0x18","bytes":"be18000000","family":"cpu","type":"mov","reloc":false,"type_num":9,"type2_num":0},{"offset":134218043,"esil":"rsp,[8],rbp,=,8,rsp,+=","refptr":false,"fcn_addr":134218016,"fcn_last":134218048,"size":1,"opcode":"pop rbp","disasm":"pop rbp","bytes":"5d","family":"cpu","type":"pop","reloc":false,"type_num":14,"type2_num":0},{"offset":134218044,"esil":"0x8000141,rip,=","refptr":false,"fcn_addr":134218016,"fcn_last":134218044,"size":5,"opcode":"jmp 0x8000141","disasm":"jmp _ZdlPvm","bytes":"e900000000","family":"cpu","type":"jmp","reloc":true,"type_num":1,"type2_num":0,"jump":134218049}]}]}]
