[{"name":"sym..text","offset":134217888,"ninstr":145,"nargs":3,"nlocals":0,"size":16,"stack":48,"type":"sym","blocks":[{"offset":134217888,"size":15,"jump":134217903,"ops":[{"offset":134217888,"ptr":134217895,"esil":"rip,rax,=","refptr":true,"fcn_addr":134217888,"fcn_last":134217897,"size":7,"opcode":"lea rax, [rip]","disasm":"lea rax, [0x080000a7]","bytes":"488d0500000000","family":"cpu","type":"lea","reloc":true,"type_num":33,"type2_num":0,"flags":["section..text","sym..text","rip"],"comment":"WzEwXSAtci14IHNlY3Rpb24gc2l6ZSAxMjEzIG5hbWVkIC50ZXh0","refs":[{"addr":134217895,"type":"DATA","perm":"r--"}]},{"offset":134217895,"esil":"rax,rdi,=[8]","refptr":true,"fcn_addr":134217888,"fcn_last":134217901,"size":3,"opcode":"mov qword [rdi], rax","disasm":"mov qword [rdi], rax","bytes":"488907","family":"cpu","type":"mov","reloc":false,"type_num":9,"type2_num":0,"xrefs":[{"addr":134217888,"type":"DATA","perm":"r--"}]},{"offset":134217898,"esil":"0x80000af,rip,=","refptr":false,"fcn_addr":134217888,"fcn_last":134217903,"size":5,"opcode":"jmp 0x80000af","disasm":"jmp _ZNSt7codecvtIwc11__mbstate_tED2Ev","bytes":"e900000000","family":"cpu","type":"jmp","reloc":true,"type_num":1,"type2_num":0,"jump":134217903,"refs":[{"addr":134217903,"type":"CODE","perm":"--x"}]},{"offset":134217899,"esil":"al,rax,+=[1],7,$o,of,:=,7,$s,sf,:=,$z,zf,:=,7,$c,cf,:=,$p,pf,:=,3,$c,af,:=","refptr":true,"fcn_addr":134217888,"fcn_last":134217902,"size":2,"opcode":"add byte [rax], al","disasm":"add byte [rax], al","bytes":"0000","family":"cpu","type":"add","reloc":true,"type_num":17,"type2_num":0,"flags":["method.std::codecvt_wchar_t__char____mbstate_t_.codecvt__"]},{"offset":134217901,"esil":"al,rax,+=[1],7,$o,of,:=,7,$s,sf,:=,$z,zf,:=,7,$c,cf,:=,$p,pf,:=,3,$c,af,:=","refptr":true,"fcn_addr":134217888,"fcn_last":134217902,"size":2,"opcode":"add byte [rax], al","disasm":"add byte [rax], al","bytes":"0000","family":"cpu","type":"add","reloc":false,"type_num":17,"type2_num":0}]},{"offset":134217903,"size":1,"jump":134217904,"ops":[{"offset":134217903,"esil":",","refptr":false,"fcn_addr":134217888,"fcn_last":134217903,"size":1,"opcode":"nop","disasm":"nop","bytes":"90","family":"cpu","type":"nop","reloc":false,"type_num":8,"type2_num":0,"xrefs":[{"addr":134217898,"type":"CODE","perm":"--x"}]}]}]}]
