[{"name":"sym.std::hash_boost::json::object_::operator___boost::json::object_const__const","offset":134237584,"ninstr":62,"nargs":1,"nlocals":2,"size":240,"stack":88,"type":"sym","blocks":[{"offset":134237584,"size":47,"jump":134237769,"fail":134237631,"ops":[{"offset":134237584,"esil":"r15,8,rsp,-,=[8],8,rsp,-=","refptr":false,"fcn_addr":134237584,"fcn_last":134237822,"size":2,"opcode":"push r15","disasm":"push r15","bytes":"4157","family":"cpu","type":"rpush","reloc":false,"type_num":268435468,"type2_num":0,"flags":["sym.std::hash_boost::json::object_::operator___boost::json::object_const__const"],"comment":"c3RkOjpoYXNoPGJvb3N0Ojpqc29uOjpvYmplY3Q+OjpvcGVyYXRvcigpKGJvb3N0Ojpqc29uOjpvYmplY3QgY29uc3QmKSBjb25zdA=="},{"offset":134237586,"esil":"r14,8,rsp,-,=[8],8,rsp,-=","refptr":false,"fcn_addr":134237584,"fcn_last":134237822,"size":2,"opcode":"push r14","disasm":"push r14","bytes":"4156","family":"cpu","type":"rpush","reloc":false,"type_num":268435468,"type2_num":0},{"offset":134237588,"esil":"r13,8,rsp,-,=[8],8,rsp,-=","refptr":false,"fcn_addr":134237584,"fcn_last":134237822,"size":2,"opcode":"push r13","disasm":"push r13","bytes":"4155","family":"cpu","type":"rpush","reloc":false,"type_num":268435468,"type2_num":0},{"offset":134237590,"esil":"r12,8,rsp,-,=[8],8,rsp,-=","refptr":false,"fcn_addr":134237584,"fcn_last":134237822,"size":2,"opcode":"push r12","disasm":"push r12","bytes":"4154","family":"cpu","type":"rpush","reloc":false,"type_num":268435468,"type2_num":0},{"offset":134237592,"esil":"rbp,8,rsp,-,=[8],8,rsp,-=","refptr":false,"fcn_addr":134237584,"fcn_last":134237823,"size":1,"opcode":"push rbp","disasm":"push rbp","bytes":"55","family":"cpu","type":"rpush","reloc":false,"type_num":268435468,"type2_num":0},{"offset":134237593,"esil":"rbx,8,rsp,-,=[8],8,rsp,-=","refptr":false,"fcn_addr":134237584,"fcn_last":134237823,"size":1,"opcode":"push rbx","disasm":"push rbx","bytes":"53","family":"cpu","type":"rpush","reloc":false,"type_num":268435468,"type2_num":0},{"offset":134237594,"val":40,"esil":"40,rsp,-=,40,0x8000000000000000,-,!,63,$o,^,of,:=,63,$s,sf,:=,$z,zf,:=,$p,pf,:=,64,$b,cf,:=,3,$b,af,:=","refptr":false,"fcn_addr":134237584,"fcn_last":134237820,"size":4,"opcode":"sub rsp, 0x28","disasm":"sub rsp, 0x28","bytes":"4883ec28","family":"cpu","type":"sub","reloc":false,"type_num":18,"type2_num":0},{"offset":134237598,"esil":"0x10,rsi,+,[8],rax,=","refptr":true,"fcn_addr":134237584,"fcn_last":134237820,"size":4,"opcode":"mov rax, qword [rsi + 0x10]","disasm":"mov rax, qword [rsi + 0x10]","bytes":"488b4610","family":"cpu","type":"mov","reloc":false,"type_num":9,"type2_num":0},{"offset":134237602,"esil":"rax,[4],r15,=","refptr":true,"fcn_addr":134237584,"fcn_last":134237821,"size":3,"opcode":"mov r15d, dword [rax]","disasm":"mov r15d, dword [rax]","bytes":"448b38","family":"cpu","type":"mov","reloc":false,"type_num":9,"type2_num":0},{"offset":134237605,"esil":"0x10,rax,+,r12,=","refptr":true,"fcn_addr":134237584,"fcn_last":134237820,"size":4,"opcode":"lea r12, [rax + 0x10]","disasm":"lea r12, [rax + 0x10]","bytes":"4c8d6010","family":"cpu","type":"lea","reloc":false,"type_num":33,"type2_num":0},{"offset":134237609,"esil":"r15,4,*,r15,+,rdx,=","refptr":true,"fcn_addr":134237584,"fcn_last":134237820,"size":4,"opcode":"lea rdx, [r15 + r15*4]","disasm":"lea rdx, [r15 + r15*4]","bytes":"4b8d14bf","family":"cpu","type":"lea","reloc":false,"type_num":33,"type2_num":0},{"offset":134237613,"esil":"0x10,rdx,8,*,rax,+,+,rax,=","refptr":true,"fcn_addr":134237584,"fcn_last":134237819,"size":5,"opcode":"lea rax, [rax + rdx*8 + 0x10]","disasm":"lea rax, [rax + rdx*8 + 0x10]","bytes":"488d44d010","family":"cpu","type":"lea","reloc":false,"type_num":33,"type2_num":0},{"offset":134237618,"esil":"rax,rsp,=[8]","refptr":true,"fcn_addr":134237584,"fcn_last":134237820,"size":4,"opcode":"mov qword [rsp], rax","disasm":"mov qword [rsp], rax","bytes":"48890424","family":"cpu","type":"mov","reloc":false,"type_num":9,"type2_num":0},{"offset":134237622,"esil":"rax,r12,==,$z,zf,:=,64,$b,cf,:=,$p,pf,:=,63,$s,sf,:=,rax,0x8000000000000000,-,!,63,$o,^,of,:=,3,$b,af,:=","refptr":false,"fcn_addr":134237584,"fcn_last":134237821,"size":3,"opcode":"cmp r12, rax","disasm":"cmp r12, rax","bytes":"4939c4","family":"cpu","type":"cmp","reloc":false,"type_num":15,"type2_num":0},{"offset":134237625,"esil":"zf,?{,134237769,rip,=,}","refptr":false,"fcn_addr":134237584,"fcn_last":134237818,"size":6,"opcode":"je 0x8004e49","disasm":"je 0x8004e49","bytes":"0f848a000000","family":"cpu","type":"cjmp","reloc":false,"type_num":2147483649,"type2_num":0,"jump":134237769,"fail":134237631}]},{"offset":134237769,"size":18,"ops":[{"offset":134237769,"val":40,"esil":"40,rsp,+=,63,$o,of,:=,63,$s,sf,:=,$z,zf,:=,63,$c,cf,:=,$p,pf,:=,3,$c,af,:=","refptr":false,"fcn_addr":134237584,"fcn_last":134237820,"size":4,"opcode":"add rsp, 0x28","disasm":"add rsp, 0x28","bytes":"4883c428","family":"cpu","type":"add","reloc":false,"type_num":17,"type2_num":0},{"offset":134237773,"esil":"r15,rax,=","refptr":false,"fcn_addr":134237584,"fcn_last":134237821,"size":3,"opcode":"mov rax, r15","disasm":"mov rax, r15","bytes":"4c89f8","family":"cpu","type":"mov","reloc":false,"type_num":9,"type2_num":0},{"offset":134237776,"esil":"rsp,[8],rbx,=,8,rsp,+=","refptr":false,"fcn_addr":134237584,"fcn_last":134237823,"size":1,"opcode":"pop rbx","disasm":"pop rbx","bytes":"5b","family":"cpu","type":"pop","reloc":false,"type_num":14,"type2_num":0},{"offset":134237777,"esil":"rsp,[8],rbp,=,8,rsp,+=","refptr":false,"fcn_addr":134237584,"fcn_last":134237823,"size":1,"opcode":"pop rbp","disasm":"pop rbp","bytes":"5d","family":"cpu","type":"pop","reloc":false,"type_num":14,"type2_num":0},{"offset":134237778,"esil":"rsp,[8],r12,=,8,rsp,+=","refptr":false,"fcn_addr":134237584,"fcn_last":134237822,"size":2,"opcode":"pop r12","disasm":"pop r12","bytes":"415c","family":"cpu","type":"pop","reloc":false,"type_num":14,"type2_num":0},{"offset":134237780,"esil":"rsp,[8],r13,=,8,rsp,+=","refptr":false,"fcn_addr":134237584,"fcn_last":134237822,"size":2,"opcode":"pop r13","disasm":"pop r13","bytes":"415d","family":"cpu","type":"pop","reloc":false,"type_num":14,"type2_num":0},{"offset":134237782,"esil":"rsp,[8],r14,=,8,rsp,+=","refptr":false,"fcn_addr":134237584,"fcn_last":134237822,"size":2,"opcode":"pop r14","disasm":"pop r14","bytes":"415e","family":"cpu","type":"pop","reloc":false,"type_num":14,"type2_num":0},{"offset":134237784,"esil":"rsp,[8],r15,=,8,rsp,+=","refptr":false,"fcn_addr":134237584,"fcn_last":134237822,"size":2,"opcode":"pop r15","disasm":"pop r15","bytes":"415f","family":"cpu","type":"pop","reloc":false,"type_num":14,"type2_num":0},{"offset":134237786,"esil":"rsp,[8],rip,=,8,rsp,+=","refptr":false,"fcn_addr":134237584,"fcn_last":134237823,"size":1,"opcode":"ret","disasm":"ret","bytes":"c3","family":"cpu","type":"ret","reloc":false,"type_num":5,"type2_num":0}]},{"offset":134237631,"size":25,"jump":134237656,"ops":[{"offset":134237631,"ptr":1099511628211,"val":1099511628211,"esil":"1099511628211,r14,=","refptr":false,"fcn_addr":134237584,"fcn_last":134237814,"size":10,"opcode":"movabs r14, 0x100000001b3","disasm":"movabs r14, 0x100000001b3","bytes":"49beb301000000010000","family":"cpu","type":"mov","reloc":false,"type_num":9,"type2_num":0},{"offset":134237641,"esil":"0x1f,rsp,+,rax,=","refptr":true,"fcn_addr":134237584,"fcn_last":134237819,"size":5,"opcode":"lea rax, [rsp + 0x1f]","disasm":"lea rax, [var_1fh]","bytes":"488d44241f","family":"cpu","type":"lea","reloc":false,"type_num":33,"type2_num":0},{"offset":134237646,"esil":"rax,0x8,rsp,+,=[8]","refptr":true,"fcn_addr":134237584,"fcn_last":134237819,"size":5,"opcode":"mov qword [rsp + 8], rax","disasm":"mov qword [var_8h], rax","bytes":"4889442408","family":"cpu","type":"mov","reloc":false,"type_num":9,"type2_num":0},{"offset":134237651,"esil":",","refptr":false,"fcn_addr":134237584,"fcn_last":134237819,"size":5,"opcode":"nop dword [rax + rax]","disasm":"nop dword [rax + rax]","bytes":"0f1f440000","family":"cpu","type":"nop","reloc":false,"type_num":8,"type2_num":0}]},{"offset":134237792,"size":32,"jump":134237725,"ops":[{"offset":134237792,"ptr":3673995259836664009,"val":3673995259836664009,"esil":"3673995259836664009,rbp,=","refptr":false,"fcn_addr":134237584,"fcn_last":134237814,"size":10,"opcode":"movabs rbp, 0x32fca739210888c9","disasm":"movabs rbp, 0x32fca739210888c9","bytes":"48bdc988082139a7fc32","family":"cpu","type":"mov","reloc":false,"type_num":9,"type2_num":0},{"offset":134237802,"val":18205582832708405568,"esil":"18205582832708405568,rbx,=","refptr":false,"fcn_addr":134237584,"fcn_last":134237814,"size":10,"opcode":"movabs rbx, 0xfca739210888c940","disasm":"movabs rbx, 0xfca739210888c940","bytes":"48bb40c988082139a7fc","family":"cpu","type":"mov","reloc":false,"type_num":9,"type2_num":0},{"offset":134237812,"val":14695981039346656037,"esil":"14695981039346656037,r13,=","refptr":false,"fcn_addr":134237584,"fcn_last":134237814,"size":10,"opcode":"movabs r13, 0xcbf29ce484222325","disasm":"movabs r13, 0xcbf29ce484222325","bytes":"49bd25232284e49cf2cb","family":"cpu","type":"mov","reloc":false,"type_num":9,"type2_num":0},{"offset":134237822,"esil":"0x8004e1d,rip,=","refptr":false,"fcn_addr":134237584,"fcn_last":134237822,"size":2,"opcode":"jmp 0x8004e1d","disasm":"jmp 0x8004e1d","bytes":"eb9d","family":"cpu","type":"jmp","reloc":false,"type_num":1,"type2_num":0,"jump":134237725,"refs":[{"addr":134237725,"type":"CODE","perm":"--x"}]}]},{"offset":134237725,"size":44,"jump":134237656,"fail":134237769,"ops":[{"offset":134237725,"esil":"0x8,rsp,+,[8],rdi,=","refptr":true,"fcn_addr":134237584,"fcn_last":134237819,"size":5,"opcode":"mov rdi, qword [rsp + 8]","disasm":"mov rdi, qword [var_8h]","bytes":"488b7c2408","family":"cpu","type":"mov","reloc":false,"type_num":9,"type2_num":0,"xrefs":[{"addr":134237822,"type":"CODE","perm":"--x"}]},{"offset":134237730,"esil":"r12,rsi,=","refptr":false,"fcn_addr":134237584,"fcn_last":134237821,"size":3,"opcode":"mov rsi, r12","disasm":"mov rsi, r12","bytes":"4c89e6","family":"cpu","type":"mov","reloc":false,"type_num":9,"type2_num":0},{"offset":134237733,"esil":"rbp,rbx,+=,63,$o,of,:=,63,$s,sf,:=,$z,zf,:=,63,$c,cf,:=,$p,pf,:=,3,$c,af,:=","refptr":false,"fcn_addr":134237584,"fcn_last":134237821,"size":3,"opcode":"add rbx, rbp","disasm":"add rbx, rbp","bytes":"4801eb","family":"cpu","type":"add","reloc":false,"type_num":17,"type2_num":0},{"offset":134237736,"ptr":2654435769,"val":2654435769,"esil":"2654435769,rbp,=","refptr":false,"fcn_addr":134237584,"fcn_last":134237819,"size":5,"opcode":"mov ebp, 0x9e3779b9","disasm":"mov ebp, 0x9e3779b9","bytes":"bdb979379e","family":"cpu","type":"mov","reloc":false,"type_num":9,"type2_num":0},{"offset":134237741,"esil":"rbp,rbx,+=,63,$o,of,:=,63,$s,sf,:=,$z,zf,:=,63,$c,cf,:=,$p,pf,:=,3,$c,af,:=","refptr":false,"fcn_addr":134237584,"fcn_last":134237821,"size":3,"opcode":"add rbx, rbp","disasm":"add rbx, rbp","bytes":"4801eb","family":"cpu","type":"add","reloc":false,"type_num":17,"type2_num":0},{"offset":134237744,"ptr":40,"val":40,"esil":"40,r12,+=,63,$o,of,:=,63,$s,sf,:=,$z,zf,:=,63,$c,cf,:=,$p,pf,:=,3,$c,af,:=","refptr":false,"fcn_addr":134237584,"fcn_last":134237820,"size":4,"opcode":"add r12, 0x28","disasm":"add r12, 0x28","bytes":"4983c428","family":"cpu","type":"add","reloc":false,"type_num":17,"type2_num":0},{"offset":134237748,"esil":"134237753,rip,8,rsp,-=,rsp,=[8],rip,=","refptr":false,"fcn_addr":134237584,"fcn_last":134237819,"size":5,"opcode":"call 0x8004e39","disasm":"call _ZNKSt4hashIN5boost4json5valueEEclERKS2_","bytes":"e800000000","family":"cpu","type":"call","reloc":true,"type_num":3,"type2_num":0,"jump":134237753,"fail":134237753,"refs":[{"addr":134237753,"type":"CALL","perm":"--x"}]},{"offset":134237753,"esil":"rax,rbx,+,rdx,=","refptr":true,"fcn_addr":134237584,"fcn_last":134237820,"size":4,"opcode":"lea rdx, [rbx + rax]","disasm":"lea rdx, [rbx + rax]","bytes":"488d1403","family":"cpu","type":"lea","reloc":false,"type_num":33,"type2_num":0,"xrefs":[{"addr":134237748,"type":"CALL","perm":"--x"}]},{"offset":134237757,"esil":"r13,rdx,^=,$z,zf,:=,$p,pf,:=,63,$s,sf,:=,0,cf,:=,0,of,:=","refptr":false,"fcn_addr":134237584,"fcn_last":134237821,"size":3,"opcode":"xor rdx, r13","disasm":"xor rdx, r13","bytes":"4c31ea","family":"cpu","type":"xor","reloc":false,"type_num":28,"type2_num":0},{"offset":134237760,"esil":"rdx,r15,^=,$z,zf,:=,$p,pf,:=,63,$s,sf,:=,0,cf,:=,0,of,:=","refptr":false,"fcn_addr":134237584,"fcn_last":134237821,"size":3,"opcode":"xor r15, rdx","disasm":"xor r15, rdx","bytes":"4931d7","family":"cpu","type":"xor","reloc":false,"type_num":28,"type2_num":0},{"offset":134237763,"esil":"r12,rsp,[8],==,$z,zf,:=,64,$b,cf,:=,$p,pf,:=,63,$s,sf,:=,r12,0x8000000000000000,-,!,63,$o,^,of,:=,3,$b,af,:=","refptr":true,"fcn_addr":134237584,"fcn_last":134237820,"size":4,"opcode":"cmp qword [rsp], r12","disasm":"cmp qword [rsp], r12","bytes":"4c392424","family":"cpu","type":"cmp","reloc":false,"type_num":15,"type2_num":0},{"offset":134237767,"esil":"zf,!,?{,134237656,rip,=,}","refptr":false,"fcn_addr":134237584,"fcn_last":134237822,"size":2,"opcode":"jne 0x8004dd8","disasm":"jne 0x8004dd8","bytes":"758f","family":"cpu","type":"cjmp","reloc":false,"type_num":2147483649,"type2_num":0,"jump":134237656,"fail":134237769}]},{"offset":134237656,"size":18,"jump":134237792,"fail":134237674,"ops":[{"offset":134237656,"esil":"0x18,r12,+,[8],rax,=","refptr":true,"fcn_addr":134237584,"fcn_last":134237819,"size":5,"opcode":"mov rax, qword [r12 + 0x18]","disasm":"mov rax, qword [r12 + 0x18]","bytes":"498b442418","family":"cpu","type":"mov","reloc":false,"type_num":9,"type2_num":0},{"offset":134237661,"esil":"0x20,r12,+,[4],rdi,=","refptr":true,"fcn_addr":134237584,"fcn_last":134237819,"size":5,"opcode":"mov edi, dword [r12 + 0x20]","disasm":"mov edi, dword [r12 + 0x20]","bytes":"418b7c2420","family":"cpu","type":"mov","reloc":false,"type_num":9,"type2_num":0},{"offset":134237666,"esil":"rax,rdi,+=,63,$o,of,:=,63,$s,sf,:=,$z,zf,:=,63,$c,cf,:=,$p,pf,:=,3,$c,af,:=","refptr":false,"fcn_addr":134237584,"fcn_last":134237821,"size":3,"opcode":"add rdi, rax","disasm":"add rdi, rax","bytes":"4801c7","family":"cpu","type":"add","reloc":false,"type_num":17,"type2_num":0},{"offset":134237669,"esil":"rax,rdi,==,$z,zf,:=,64,$b,cf,:=,$p,pf,:=,63,$s,sf,:=,rax,0x8000000000000000,-,!,63,$o,^,of,:=,3,$b,af,:=","refptr":false,"fcn_addr":134237584,"fcn_last":134237821,"size":3,"opcode":"cmp rdi, rax","disasm":"cmp rdi, rax","bytes":"4839c7","family":"cpu","type":"cmp","reloc":false,"type_num":15,"type2_num":0},{"offset":134237672,"esil":"zf,?{,134237792,rip,=,}","refptr":false,"fcn_addr":134237584,"fcn_last":134237822,"size":2,"opcode":"je 0x8004e60","disasm":"je 0x8004e60","bytes":"7476","family":"cpu","type":"cjmp","reloc":false,"type_num":2147483649,"type2_num":0,"jump":134237792,"fail":134237674}]},{"offset":134237674,"size":14,"jump":134237688,"ops":[{"offset":134237674,"val":14695981039346656037,"esil":"14695981039346656037,r13,=","refptr":false,"fcn_addr":134237584,"fcn_last":134237814,"size":10,"opcode":"movabs r13, 0xcbf29ce484222325","disasm":"movabs r13, 0xcbf29ce484222325","bytes":"49bd25232284e49cf2cb","family":"cpu","type":"mov","reloc":false,"type_num":9,"type2_num":0},{"offset":134237684,"esil":",","refptr":false,"fcn_addr":134237584,"fcn_last":134237820,"size":4,"opcode":"nop dword [rax]","disasm":"nop dword [rax]","bytes":"0f1f4000","family":"cpu","type":"nop","reloc":false,"type_num":8,"type2_num":0}]},{"offset":134237688,"size":23,"jump":134237688,"fail":134237711,"ops":[{"offset":134237688,"esil":"8,rax,[1],~,rdx,=","refptr":true,"fcn_addr":134237584,"fcn_last":134237820,"size":4,"opcode":"movsx rdx, byte [rax]","disasm":"movsx rdx, byte [rax]","bytes":"480fbe10","family":"cpu","type":"mov","reloc":false,"type_num":9,"type2_num":0},{"offset":134237692,"val":1,"esil":"1,rax,+=,63,$o,of,:=,63,$s,sf,:=,$z,zf,:=,63,$c,cf,:=,$p,pf,:=,3,$c,af,:=","refptr":false,"fcn_addr":134237584,"fcn_last":134237820,"size":4,"opcode":"add rax, 1","disasm":"add rax, 1","bytes":"4883c001","family":"cpu","type":"add","reloc":false,"type_num":17,"type2_num":0},{"offset":134237696,"esil":"r13,rdx,^=,$z,zf,:=,$p,pf,:=,63,$s,sf,:=,0,cf,:=,0,of,:=","refptr":false,"fcn_addr":134237584,"fcn_last":134237821,"size":3,"opcode":"xor rdx, r13","disasm":"xor rdx, r13","bytes":"4c31ea","family":"cpu","type":"xor","reloc":false,"type_num":28,"type2_num":0},{"offset":134237699,"esil":"64,rdx,~,64,r14,~,*,DUP,rdx,=,64,rdx,~,-,!,!,DUP,cf,:=,of,:=","refptr":false,"fcn_addr":134237584,"fcn_last":134237820,"size":4,"opcode":"imul rdx, r14","disasm":"imul rdx, r14","bytes":"490fafd6","family":"cpu","type":"mul","reloc":false,"type_num":20,"type2_num":0},{"offset":134237703,"esil":"rdx,r13,=","refptr":false,"fcn_addr":134237584,"fcn_last":134237821,"size":3,"opcode":"mov r13, rdx","disasm":"mov r13, rdx","bytes":"4989d5","family":"cpu","type":"mov","reloc":false,"type_num":9,"type2_num":0},{"offset":134237706,"esil":"rdi,rax,==,$z,zf,:=,64,$b,cf,:=,$p,pf,:=,63,$s,sf,:=,rdi,0x8000000000000000,-,!,63,$o,^,of,:=,3,$b,af,:=","refptr":false,"fcn_addr":134237584,"fcn_last":134237821,"size":3,"opcode":"cmp rax, rdi","disasm":"cmp rax, rdi","bytes":"4839f8","family":"cpu","type":"cmp","reloc":false,"type_num":15,"type2_num":0},{"offset":134237709,"esil":"zf,!,?{,134237688,rip,=,}","refptr":false,"fcn_addr":134237584,"fcn_last":134237822,"size":2,"opcode":"jne 0x8004df8","disasm":"jne 0x8004df8","bytes":"75e9","family":"cpu","type":"cjmp","reloc":false,"type_num":2147483649,"type2_num":0,"jump":134237688,"fail":134237711}]},{"offset":134237711,"size":14,"jump":134237725,"ops":[{"offset":134237711,"esil":"rdx,rbx,=","refptr":false,"fcn_addr":134237584,"fcn_last":134237821,"size":3,"opcode":"mov rbx, rdx","disasm":"mov rbx, rdx","bytes":"4889d3","family":"cpu","type":"mov","reloc":false,"type_num":9,"type2_num":0},{"offset":134237714,"esil":"rdx,rbp,=","refptr":false,"fcn_addr":134237584,"fcn_last":134237821,"size":3,"opcode":"mov rbp, rdx","disasm":"mov rbp, rdx","bytes":"4889d5","family":"cpu","type":"mov","reloc":false,"type_num":9,"type2_num":0},{"offset":134237717,"esil":"0,6,!,!,?{,1,6,-,rbx,<<,0x8000000000000000,&,!,!,^,},6,rbx,<<=,$z,zf,:=,$p,pf,:=,63,$s,sf,:=,cf,=","refptr":false,"fcn_addr":134237584,"fcn_last":134237820,"size":4,"opcode":"shl rbx, 6","disasm":"shl rbx, 6","bytes":"48c1e306","family":"cpu","type":"shl","reloc":false,"type_num":23,"type2_num":0},{"offset":134237721,"val":2,"esil":"0,cf,:=,1,2,-,1,<<,rbp,&,?{,1,cf,:=,},2,rbp,>>,rbp,=,$z,zf,:=,$p,pf,:=,63,$s,sf,:=","refptr":false,"fcn_addr":134237584,"fcn_last":134237820,"size":4,"opcode":"shr rbp, 2","disasm":"shr rbp, 2","bytes":"48c1ed02","family":"cpu","type":"shr","reloc":false,"type_num":22,"type2_num":0}]}]}]
